databricks_parallel_run.py
databricks_parallel_run-0.0.4.dist-info/LICENCE.txt
databricks_parallel_run-0.0.4.dist-info/METADATA
databricks_parallel_run-0.0.4.dist-info/WHEEL
databricks_parallel_run-0.0.4.dist-info/top_level.txt
databricks_parallel_run-0.0.4.dist-info/RECORD
