Metadata-Version: 2.1
Name: databricks-parallel-run
Version: 0.0.4
Summary: Run databricks notebooks in parallel
Author: Kuldeep Rathore
Keywords: python,databricks,notebook,databricks parallel run,databricks parallel notebook run,paralle processing
Classifier: Programming Language :: Python :: 3
Classifier: License :: OSI Approved :: MIT License
Classifier: Operating System :: OS Independent
Requires-Python: >=3.6
License-File: LICENCE.txt
Requires-Dist: pyspark
Requires-Dist: dbutils
